examples/advanced_custom.py
examples/basic_usage.py
saucypass/__init__.py
saucypass/cli.py
saucypass/generator.py
saucypass/questions.py
saucypass/security.py
saucypass-1.0.0.dist-info/licenses/LICENSE
tests/test_generator.py
tests/test_questions.py
tests/test_security.py
saucypass-1.0.0.dist-info/METADATA
saucypass-1.0.0.dist-info/WHEEL
saucypass-1.0.0.dist-info/top_level.txt
saucypass-1.0.0.dist-info/RECORD
