Metadata-Version: 2.4
Name: SaucyPass
Version: 1.0.0
Summary: Generate memorable passwords from personal cues
License: Unlicense
Classifier: License :: Public Domain
Classifier: Programming Language :: Python :: 3
Requires-Python: >=3.8
License-File: LICENSE
Dynamic: license-file
